{"stocks": [{"ticker": "2388.HK", "name": "2388.HK", "price": 44.12, "change": -0.34, "changePercent": -0.76, "change5dPercent": -0.68, "marketCap": 466471054042, "volume": 1239459, "avgVolume10d": 10419107, "avgVolume60d": 12103345, "avgVolume90d": 11267107, "avgTradingValue": 488186218, "sma10": 44.07, "sma20": 42.87, "sma30": 42.4, "sma50": 42.63, "sma100": 40.76, "sma200": 38.68, "sector": "", "indices": []}, {"ticker": "2359.HK", "name": "2359.HK", "price": 122.7, "change": -1.1, "changePercent": -0.89, "change5dPercent": -5.62, "marketCap": 371946520030, "volume": 547000, "avgVolume10d": 3903373, "avgVolume60d": 4716055, "avgVolume90d": 4883297, "avgTradingValue": 578650090, "sma10": 127.2, "sma20": 120.84, "sma30": 116.87, "sma50": 117.35, "sma100": 112.29, "sma200": 107.81, "sector": "", "indices": []}, {"ticker": "6869.HK", "name": "YOFC", "price": 208.6, "change": -2.4, "changePercent": -1.14, "change5dPercent": -3.6, "marketCap": 295836305893, "volume": 2630388, "avgVolume10d": 22263400, "avgVolume60d": 28008464, "avgVolume90d": 29088099, "avgTradingValue": 5065918520, "sma10": 216.8, "sma20": 196.28, "sma30": 182.2, "sma50": 158.13, "sma100": 103.53, "sma200": 70.42, "sector": "Technology", "indices": []}, {"ticker": "1772.HK", "name": "GANFENGLITHIUM", "price": 83.4, "change": 2.8, "changePercent": 3.47, "change5dPercent": 1.03, "marketCap": 220679468938, "volume": 3107189, "avgVolume10d": 12025303, "avgVolume60d": 14434690, "avgVolume90d": 15101877, "avgTradingValue": 1168957974, "sma10": 80.44, "sma20": 74.08, "sma30": 69.5, "sma50": 66.55, "sma100": 61.21, "sma200": 49.08, "sector": "Basic Materials", "indices": []}, {"ticker": "0002.HK", "name": "0002.HK", "price": 75.1, "change": 0.15, "changePercent": 0.2, "change5dPercent": 0.13, "marketCap": 189736433951, "volume": 514728, "avgVolume10d": 2726439, "avgVolume60d": 3608213, "avgVolume90d": 3636329, "avgTradingValue": 216727017, "sma10": 74.69, "sma20": 73.99, "sma30": 73.81, "sma50": 73.95, "sma100": 71.42, "sma200": 67.81, "sector": "", "indices": []}, {"ticker": "1072.HK", "name": "DONGFANG ELEC", "price": 41.22, "change": -0.48, "changePercent": -1.15, "change5dPercent": 5.1, "marketCap": 153649468644, "volume": 1145800, "avgVolume10d": 11340976, "avgVolume60d": 16647951, "avgVolume90d": 14689643, "avgTradingValue": 515025881, "sma10": 40.29, "sma20": 38.28, "sma30": 39.13, "sma50": 36.85, "sma100": 30.46, "sma200": 24.13, "sector": "Industrials", "indices": []}, {"ticker": "0288.HK", "name": "WH GROUP", "price": 10.7, "change": 0.11, "changePercent": 1.04, "change5dPercent": 0.09, "marketCap": 137155041616, "volume": 3751440, "avgVolume10d": 29167957, "avgVolume60d": 30001320, "avgVolume90d": 29272224, "avgTradingValue": 337913562, "sma10": 10.62, "sma20": 10.3, "sma30": 10.08, "sma50": 9.96, "sma100": 9.31, "sma200": 8.54, "sector": "Consumer Defensive", "indices": []}, {"ticker": "2208.HK", "name": "GOLDWIND", "price": 16.6, "change": -0.33, "changePercent": -1.95, "change5dPercent": 9.93, "marketCap": 131036432241, "volume": 7425000, "avgVolume10d": 33343493, "avgVolume60d": 36175241, "avgVolume90d": 44137746, "avgTradingValue": 513013124, "sma10": 15.09, "sma20": 14.86, "sma30": 15.08, "sma50": 14.67, "sma100": 14.35, "sma200": 12.39, "sector": "Industrials", "indices": []}, {"ticker": "3808.HK", "name": "SINOTRUK", "price": 42.46, "change": 0.52, "changePercent": 1.24, "change5dPercent": -6.06, "marketCap": 117342216950, "volume": 822500, "avgVolume10d": 21708888, "avgVolume60d": 10758974, "avgVolume90d": 8941124, "avgTradingValue": 640812390, "sma10": 43.45, "sma20": 41.63, "sma30": 40.2, "sma50": 40.24, "sma100": 34.85, "sma200": 29.21, "sector": "Industrials", "indices": []}, {"ticker": "1308.HK", "name": "SITC", "price": 34.64, "change": 0.12, "changePercent": 0.35, "change5dPercent": -0.35, "marketCap": 92803588325, "volume": 668606, "avgVolume10d": 4505129, "avgVolume60d": 5620756, "avgVolume90d": 5355492, "avgTradingValue": 186213691, "sma10": 35.16, "sma20": 34.69, "sma30": 34.46, "sma50": 33.35, "sma100": 30.18, "sma200": 28.49, "sector": "Industrials", "indices": []}, {"ticker": "1888.HK", "name": "KB LAMINATES", "price": 28.62, "change": 0.28, "changePercent": 0.99, "change5dPercent": 15.22, "marketCap": 89795706086, "volume": 4810200, "avgVolume10d": 31118564, "avgVolume60d": 27588877, "avgVolume90d": 22559603, "avgTradingValue": 581857320, "sma10": 25.39, "sma20": 22.74, "sma30": 22.43, "sma50": 21.35, "sma100": 17.03, "sma200": 14.31, "sector": "Technology", "indices": []}, {"ticker": "2319.HK", "name": "MENGNIU DAIRY", "price": 16.68, "change": 0.19, "changePercent": 1.15, "change5dPercent": -1.77, "marketCap": 64546784537, "volume": 2584500, "avgVolume10d": 18555236, "avgVolume60d": 26858526, "avgVolume90d": 24502211, "avgTradingValue": 381617175, "sma10": 16.91, "sma20": 16.78, "sma30": 16.63, "sma50": 16.57, "sma100": 15.88, "sma200": 15.69, "sector": "Consumer Defensive", "indices": []}, {"ticker": "3931.HK", "name": "CALB", "price": 35.92, "change": -0.44, "changePercent": -1.21, "change5dPercent": -4.62, "marketCap": 63625639442, "volume": 536600, "avgVolume10d": 8265046, "avgVolume60d": 5652309, "avgVolume90d": 5480810, "avgTradingValue": 311590937, "sma10": 36.46, "sma20": 33.82, "sma30": 31.78, "sma50": 29.58, "sma100": 28.29, "sma200": 27.06, "sector": "Industrials", "indices": []}, {"ticker": "0522.HK", "name": "ASMPT", "price": 140.4, "change": 1.8, "changePercent": 1.3, "change5dPercent": 11.87, "marketCap": 58410927338, "volume": 923492, "avgVolume10d": 3759825, "avgVolume60d": 2793434, "avgVolume90d": 2631846, "avgTradingValue": 316889947, "sma10": 125.54, "sma20": 114.81, "sma30": 112.75, "sma50": 109.97, "sma100": 97.54, "sma200": 85.53, "sector": "Technology", "indices": []}, {"ticker": "2331.HK", "name": "LI NING", "price": 21.48, "change": 0.14, "changePercent": 0.66, "change5dPercent": -2.54, "marketCap": 55311518336, "volume": 1288000, "avgVolume10d": 18834476, "avgVolume60d": 21812185, "avgVolume90d": 21112677, "avgTradingValue": 494807644, "sma10": 21.77, "sma20": 21.66, "sma30": 21.09, "sma50": 21.29, "sma100": 20.1, "sma200": 18.61, "sector": "Consumer Cyclical", "indices": []}, {"ticker": "1729.HK", "name": "TIME INTERCON", "price": 21.84, "change": 0.02, "changePercent": 0.09, "change5dPercent": 17.23, "marketCap": 45588490536, "volume": 1857000, "avgVolume10d": 22291016, "avgVolume60d": 17593291, "avgVolume90d": 14601097, "avgTradingValue": 323410263, "sma10": 19.71, "sma20": 17.73, "sma30": 17.21, "sma50": 17.4, "sma100": 16.75, "sma200": 14.84, "sector": "Industrials", "indices": []}, {"ticker": "0148.HK", "name": "KINGBOARD HLDG", "price": 41.16, "change": -0.52, "changePercent": -1.25, "change5dPercent": 2.03, "marketCap": 45462947959, "volume": 1583000, "avgVolume10d": 8341046, "avgVolume60d": 5304300, "avgVolume90d": 4129483, "avgTradingValue": 243528693, "sma10": 39.38, "sma20": 36.89, "sma30": 37.1, "sma50": 36.66, "sma100": 32.39, "sma200": 29.5, "sector": "Industrials", "indices": []}, {"ticker": "1070.HK", "name": "TCL ELECTRONICS", "price": 14.31, "change": -0.03, "changePercent": -0.21, "change5dPercent": 3.85, "marketCap": 35997561354, "volume": 605000, "avgVolume10d": 7798779, "avgVolume60d": 10165551, "avgVolume90d": 8724146, "avgTradingValue": 184146677, "sma10": 14.11, "sma20": 13.05, "sma30": 12.63, "sma50": 12.5, "sma100": 11.67, "sma200": 10.8, "sector": "Technology", "indices": []}, {"ticker": "2252.HK", "name": "MEDBOT-B", "price": 34.5, "change": 0.38, "changePercent": 1.11, "change5dPercent": 13.86, "marketCap": 35601523498, "volume": 636500, "avgVolume10d": 7508197, "avgVolume60d": 7848301, "avgVolume90d": 7229835, "avgTradingValue": 211707630, "sma10": 31.12, "sma20": 28.07, "sma30": 26.89, "sma50": 26.83, "sma100": 25.65, "sma200": 24.73, "sector": "Healthcare", "indices": []}, {"ticker": "3393.HK", "name": "WASION HOLDINGS", "price": 30.36, "change": -1.58, "changePercent": -4.95, "change5dPercent": 1.4, "marketCap": 30022865596, "volume": 52136700, "avgVolume10d": 9765131, "avgVolume60d": 5666714, "avgVolume90d": 4683287, "avgTradingValue": 220313506, "sma10": 31.2, "sma20": 29.88, "sma30": 29.24, "sma50": 28.08, "sma100": 22.96, "sma200": 16.98, "sector": "Industrials", "indices": []}, {"ticker": "1797.HK", "name": "EAST BUY", "price": 27.82, "change": -1.2, "changePercent": -4.14, "change5dPercent": -2.04, "marketCap": 29478286419, "volume": 2505000, "avgVolume10d": 7461129, "avgVolume60d": 11562751, "avgVolume90d": 10933256, "avgTradingValue": 259760621, "sma10": 29.06, "sma20": 28.01, "sma30": 27.2, "sma50": 27.37, "sma100": 23.83, "sma200": 23.45, "sector": "Consumer Defensive", "indices": []}], "totalUniverse": 496, "totalPassing": 21, "lastUpdated": "2026-04-21T02:04:44.627712"}