{"stocks": [{"ticker": "XOM", "name": "Exxon Mobil Corporation", "price": 159.62, "change": 2.39, "changePercent": 1.52, "change5dPercent": 7.76, "marketCap": 665015472530, "volume": 4287804, "avgVolume10d": 19690050, "avgVolume60d": 20176070, "avgVolume90d": 18571111, "avgTradingValue": 3115663264, "sma10": 152.84, "sma20": 151.68, "sma30": 150.53, "sma50": 142.26, "sma100": 129.16, "sma200": 118.84, "sector": "Energy", "indices": []}, {"ticker": "CVX", "name": "Chevron Corporation", "price": 199.46, "change": 2.62, "changePercent": 1.33, "change5dPercent": 7.07, "marketCap": 398491160536, "volume": 2717455, "avgVolume10d": 13262005, "avgVolume60d": 11529275, "avgVolume90d": 10614488, "avgTradingValue": 2239076338, "sma10": 192.35, "sma20": 188.99, "sma30": 186.02, "sma50": 177.31, "sma100": 163.69, "sma200": 155.89, "sector": "Energy", "indices": []}, {"ticker": "RTX", "name": "RTX Corporation", "price": 202.39, "change": -3.67, "changePercent": -1.78, "change5dPercent": -2.23, "marketCap": 272102153244, "volume": 1029127, "avgVolume10d": 5608082, "avgVolume60d": 6053045, "avgVolume90d": 5534124, "avgTradingValue": 1407414877, "sma10": 206.09, "sma20": 204.5, "sma30": 202.36, "sma50": 199.39, "sma100": 187.79, "sma200": 170.02, "sector": "Industrials", "indices": []}, {"ticker": "SHEL", "name": "Shell PLC", "price": 92.58, "change": 2.1, "changePercent": 2.32, "change5dPercent": 8.78, "marketCap": 262465786608, "volume": 2287704, "avgVolume10d": 6848631, "avgVolume60d": 5762540, "avgVolume90d": 5198750, "avgTradingValue": 494637302, "sma10": 86.93, "sma20": 84.11, "sma30": 81.74, "sma50": 78.27, "sma100": 75.67, "sma200": 72.82, "sector": "Energy", "indices": []}, {"ticker": "VZ", "name": "Verizon Communications Inc.", "price": 50.85, "change": -0.12, "changePercent": -0.23, "change5dPercent": 0.29, "marketCap": 214511419358, "volume": 5286970, "avgVolume10d": 21793497, "avgVolume60d": 30455091, "avgVolume90d": 28856585, "avgTradingValue": 1224447080, "sma10": 50.92, "sma20": 50.19, "sma30": 49.37, "sma50": 45.62, "sma100": 42.65, "sma200": 41.99, "sector": "Communication Services", "indices": []}, {"ticker": "COP", "name": "ConocoPhillips", "price": 122.96, "change": 1.64, "changePercent": 1.36, "change5dPercent": 7.72, "marketCap": 150280486669, "volume": 1719727, "avgVolume10d": 10165072, "avgVolume60d": 8831695, "avgVolume90d": 8336132, "avgTradingValue": 1141575030, "sma10": 118.42, "sma20": 115.41, "sma30": 112.78, "sma50": 106.81, "sma100": 98.18, "sma200": 94.66, "sector": "Energy", "indices": []}, {"ticker": "PBR", "name": "Petroleo Brasileiro S.A. Petrob", "price": 19.85, "change": 0.68, "changePercent": 3.57, "change5dPercent": 10.37, "marketCap": 128033451041, "volume": 10821227, "avgVolume10d": 37500932, "avgVolume60d": 25970023, "avgVolume90d": 23891429, "avgTradingValue": 552665420, "sma10": 18.28, "sma20": 17.33, "sma30": 16.62, "sma50": 15.29, "sma100": 13.78, "sma200": 13.0, "sector": "Energy", "indices": []}, {"ticker": "ENB", "name": "Enbridge Inc", "price": 54.44, "change": -0.1, "changePercent": -0.17, "change5dPercent": 1.39, "marketCap": 118844291750, "volume": 699763, "avgVolume10d": 3799476, "avgVolume60d": 4966482, "avgVolume90d": 4769699, "avgTradingValue": 243099018, "sma10": 54.01, "sma20": 53.25, "sma30": 52.32, "sma50": 49.99, "sma100": 48.47, "sma200": 47.25, "sector": "Energy", "indices": []}, {"ticker": "BP", "name": "BP p.l.c.", "price": 44.1, "change": 1.19, "changePercent": 2.79, "change5dPercent": 10.4, "marketCap": 112982011760, "volume": 9038303, "avgVolume10d": 15329710, "avgVolume60d": 10551128, "avgVolume90d": 9363370, "avgTradingValue": 504735736, "sma10": 41.26, "sma20": 39.86, "sma30": 39.16, "sma50": 37.66, "sma100": 36.26, "sma200": 34.01, "sector": "Energy", "indices": []}, {"ticker": "SBUX", "name": "Starbucks Corporation", "price": 98.51, "change": 0.69, "changePercent": 0.71, "change5dPercent": -2.24, "marketCap": 112055855324, "volume": 933360, "avgVolume10d": 8231856, "avgVolume60d": 9239667, "avgVolume90d": 9416844, "avgTradingValue": 743393312, "sma10": 99.25, "sma20": 98.01, "sma30": 97.41, "sma50": 95.13, "sma100": 89.59, "sma200": 88.43, "sector": "Consumer Cyclical", "indices": []}, {"ticker": "DUK", "name": "Duke Energy Corporation (Holdin", "price": 133.91, "change": 0.45, "changePercent": 0.33, "change5dPercent": 3.25, "marketCap": 104178728639, "volume": 1328967, "avgVolume10d": 4994266, "avgVolume60d": 4282746, "avgVolume90d": 4056061, "avgTradingValue": 615769328, "sma10": 131.91, "sma20": 130.29, "sma30": 127.94, "sma50": 123.78, "sma100": 121.62, "sma200": 120.01, "sector": "Utilities", "indices": []}, {"ticker": "VRT", "name": "Vertiv Holdings, LLC", "price": 268.3, "change": 3.56, "changePercent": 1.34, "change5dPercent": -0.65, "marketCap": 102628208247, "volume": 1602577, "avgVolume10d": 8062927, "avgVolume60d": 6148227, "avgVolume90d": 6602499, "avgTradingValue": 1770681077, "sma10": 260.28, "sma20": 255.49, "sma30": 240.69, "sma50": 215.68, "sma100": 195.23, "sma200": 165.18, "sector": "Industrials", "indices": []}, {"ticker": "CNQ", "name": "Canadian Natural Resources Limi", "price": 48.6, "change": -0.19, "changePercent": -0.38, "change5dPercent": 6.31, "marketCap": 101419956411, "volume": 3024866, "avgVolume10d": 11630436, "avgVolume60d": 9568231, "avgVolume90d": 9010129, "avgTradingValue": 465806925, "sma10": 46.94, "sma20": 44.94, "sma30": 43.07, "sma50": 39.64, "sma100": 36.21, "sma200": 33.83, "sector": "Energy", "indices": []}, {"ticker": "EQNR", "name": "Equinor ASA", "price": 36.88, "change": 1.24, "changePercent": 3.49, "change5dPercent": 13.67, "marketCap": 91900874281, "volume": 1764745, "avgVolume10d": 8978544, "avgVolume60d": 5835890, "avgVolume90d": 5148047, "avgTradingValue": 249518663, "sma10": 33.75, "sma20": 31.64, "sma30": 30.13, "sma50": 27.94, "sma100": 25.5, "sma200": 24.81, "sector": "Energy", "indices": []}, {"ticker": "WMB", "name": "Williams Companies, Inc. (The)", "price": 74.76, "change": 0.88, "changePercent": 1.18, "change5dPercent": 1.98, "marketCap": 91360706190, "volume": 777799, "avgVolume10d": 5753399, "avgVolume60d": 7130769, "avgVolume90d": 7136488, "avgTradingValue": 462417766, "sma10": 73.8, "sma20": 73.6, "sma30": 71.99, "sma50": 68.13, "sma100": 63.5, "sma200": 60.96, "sector": "Energy", "indices": []}, {"ticker": "EPD", "name": "Enterprise Products Partners L.", "price": 37.78, "change": 0.46, "changePercent": 1.23, "change5dPercent": 2.88, "marketCap": 81736174392, "volume": 774076, "avgVolume10d": 3541167, "avgVolume60d": 4399694, "avgVolume90d": 4207426, "avgTradingValue": 139315273, "sma10": 37.17, "sma20": 36.77, "sma30": 36.34, "sma50": 34.7, "sma100": 32.96, "sma200": 31.56, "sector": "Energy", "indices": []}, {"ticker": "KMI", "name": "Kinder Morgan, Inc.", "price": 33.79, "change": 0.48, "changePercent": 1.46, "change5dPercent": 2.53, "marketCap": 75176210191, "volume": 1761882, "avgVolume10d": 11679438, "avgVolume60d": 13406099, "avgVolume90d": 13477470, "avgTradingValue": 416461184, "sma10": 33.41, "sma20": 33.2, "sma30": 32.49, "sma50": 30.76, "sma100": 28.64, "sma200": 27.76, "sector": "Energy", "indices": []}, {"ticker": "SU", "name": "Suncor Energy  Inc.", "price": 61.21, "change": 0.59, "changePercent": 0.97, "change5dPercent": 6.86, "marketCap": 72972813664, "volume": 1071505, "avgVolume10d": 5046100, "avgVolume60d": 4997598, "avgVolume90d": 4978343, "avgTradingValue": 308583551, "sma10": 58.59, "sma20": 57.25, "sma30": 56.19, "sma50": 53.3, "sma100": 48.0, "sma200": 43.69, "sector": "Energy", "indices": []}, {"ticker": "VLO", "name": "Valero Energy Corporation", "price": 236.23, "change": 3.66, "changePercent": 1.58, "change5dPercent": 8.85, "marketCap": 72021904169, "volume": 551827, "avgVolume10d": 4116102, "avgVolume60d": 3457767, "avgVolume90d": 3232701, "avgTradingValue": 761514817, "sma10": 227.75, "sma20": 215.72, "sma30": 209.92, "sma50": 199.04, "sma100": 184.67, "sma200": 165.04, "sector": "Energy", "indices": []}, {"ticker": "PSX", "name": "Phillips 66", "price": 174.49, "change": 1.01, "changePercent": 0.58, "change5dPercent": 7.38, "marketCap": 69693394333, "volume": 761975, "avgVolume10d": 3680967, "avgVolume60d": 2693341, "avgVolume90d": 2588563, "avgTradingValue": 524264139, "sma10": 168.69, "sma20": 161.98, "sma30": 159.74, "sma50": 151.65, "sma100": 142.87, "sma200": 133.38, "sector": "Energy", "indices": []}, {"ticker": "OXY", "name": "Occidental Petroleum Corporatio", "price": 57.88, "change": 0.63, "changePercent": 1.09, "change5dPercent": 8.95, "marketCap": 57075250329, "volume": 3886045, "avgVolume10d": 21666994, "avgVolume60d": 13932829, "avgVolume90d": 12367600, "avgTradingValue": 1065659827, "sma10": 55.52, "sma20": 53.55, "sma30": 50.99, "sma50": 47.86, "sma100": 44.39, "sma200": 44.14, "sector": "Energy", "indices": []}, {"ticker": "OKE", "name": "ONEOK, Inc.", "price": 86.71, "change": 1.39, "changePercent": 1.64, "change5dPercent": 2.4, "marketCap": 54715600392, "volume": 614299, "avgVolume10d": 4080979, "avgVolume60d": 4483643, "avgVolume90d": 4456917, "avgTradingValue": 423196434, "sma10": 85.6, "sma20": 85.36, "sma30": 84.53, "sma50": 80.42, "sma100": 75.16, "sma200": 74.63, "sector": "Energy", "indices": []}, {"ticker": "TGT", "name": "Target Corporation", "price": 117.61, "change": 0.56, "changePercent": 0.48, "change5dPercent": -2.59, "marketCap": 53251287052, "volume": 941576, "avgVolume10d": 5472717, "avgVolume60d": 6639556, "avgVolume90d": 6900580, "avgTradingValue": 716930932, "sma10": 118.86, "sma20": 117.23, "sma30": 115.93, "sma50": 111.66, "sma100": 101.73, "sma200": 97.89, "sector": "Consumer Defensive", "indices": []}, {"ticker": "FANG", "name": "Diamondback Energy, Inc.", "price": 186.7, "change": 4.37, "changePercent": 2.4, "change5dPercent": 4.67, "marketCap": 53197754396, "volume": 551780, "avgVolume10d": 4365468, "avgVolume60d": 2572651, "avgVolume90d": 2284339, "avgTradingValue": 678125563, "sma10": 180.15, "sma20": 176.38, "sma30": 172.88, "sma50": 164.32, "sma100": 155.98, "sma200": 148.17, "sector": "Energy", "indices": []}, {"ticker": "EXC", "name": "Exelon Corporation", "price": 50.38, "change": 0.09, "changePercent": 0.19, "change5dPercent": 2.81, "marketCap": 51533329524, "volume": 1407699, "avgVolume10d": 9249359, "avgVolume60d": 8322809, "avgVolume90d": 8193214, "avgTradingValue": 447970848, "sma10": 49.43, "sma20": 48.77, "sma30": 47.48, "sma50": 45.97, "sma100": 45.37, "sma200": 44.29, "sector": "Utilities", "indices": []}, {"ticker": "CVE", "name": "Cenovus Energy Inc", "price": 23.63, "change": 0.28, "changePercent": 1.2, "change5dPercent": 4.89, "marketCap": 44600187195, "volume": 1895470, "avgVolume10d": 16881837, "avgVolume60d": 14122102, "avgVolume90d": 12955418, "avgTradingValue": 378288032, "sma10": 23.08, "sma20": 22.69, "sma30": 22.07, "sma50": 20.43, "sma100": 18.88, "sma200": 17.13, "sector": "Energy", "indices": []}, {"ticker": "VTR", "name": "Ventas, Inc.", "price": 88.07, "change": 0.28, "changePercent": 0.32, "change5dPercent": 2.31, "marketCap": 41834937799, "volume": 578802, "avgVolume10d": 2770320, "avgVolume60d": 2932313, "avgVolume90d": 3001676, "avgTradingValue": 239873825, "sma10": 86.33, "sma20": 86.28, "sma30": 85.11, "sma50": 81.72, "sma100": 79.31, "sma200": 72.55, "sector": "Real Estate", "indices": []}, {"ticker": "EQT", "name": "EQT Corporation", "price": 65.47, "change": 1.16, "changePercent": 1.8, "change5dPercent": 5.89, "marketCap": 40843128355, "volume": 750864, "avgVolume10d": 7954466, "avgVolume60d": 9754242, "avgVolume90d": 9297250, "avgTradingValue": 562843625, "sma10": 63.16, "sma20": 61.59, "sma30": 59.85, "sma50": 57.27, "sma100": 56.75, "sma200": 55.23, "sector": "Energy", "indices": []}, {"ticker": "ERIC", "name": "Ericsson", "price": 12.07, "change": 0.1, "changePercent": 0.88, "change5dPercent": 6.86, "marketCap": 40637625593, "volume": 5799032, "avgVolume10d": 9246373, "avgVolume60d": 8964155, "avgVolume90d": 9389022, "avgTradingValue": 92417640, "sma10": 11.48, "sma20": 11.38, "sma30": 11.29, "sma50": 10.75, "sma100": 10.2, "sma200": 9.09, "sector": "Technology", "indices": []}, {"ticker": "NTR", "name": "Nutrien Ltd.", "price": 79.18, "change": 1.39, "changePercent": 1.79, "change5dPercent": 4.06, "marketCap": 38268420022, "volume": 1110785, "avgVolume10d": 5357058, "avgVolume60d": 3285821, "avgVolume90d": 3079570, "avgTradingValue": 329832718, "sma10": 77.92, "sma20": 75.4, "sma30": 73.73, "sma50": 70.6, "sma100": 64.78, "sma200": 61.71, "sector": "Basic Materials", "indices": []}, {"ticker": "ADM", "name": "Archer-Daniels-Midland Company", "price": 72.36, "change": 1.61, "changePercent": 2.28, "change5dPercent": 4.28, "marketCap": 34793299477, "volume": 759068, "avgVolume10d": 3826366, "avgVolume60d": 3589989, "avgVolume90d": 3431748, "avgTradingValue": 236154001, "sma10": 69.69, "sma20": 68.92, "sma30": 68.44, "sma50": 66.81, "sma100": 62.65, "sma200": 59.43, "sector": "Consumer Defensive", "indices": []}, {"ticker": "QSR", "name": "Restaurant Brands International", "price": 75.33, "change": 0.76, "changePercent": 1.02, "change5dPercent": 4.63, "marketCap": 34317195800, "volume": 579035, "avgVolume10d": 3862243, "avgVolume60d": 3132353, "avgVolume90d": 3014073, "avgTradingValue": 240456995, "sma10": 73.07, "sma20": 71.33, "sma30": 70.55, "sma50": 69.58, "sma100": 69.17, "sma200": 67.27, "sector": "Consumer Cyclical", "indices": []}, {"ticker": "FE", "name": "FirstEnergy Corp.", "price": 51.71, "change": -0.05, "changePercent": -0.11, "change5dPercent": 2.06, "marketCap": 29879130285, "volume": 527013, "avgVolume10d": 3863281, "avgVolume60d": 4583793, "avgVolume90d": 4622791, "avgTradingValue": 214717360, "sma10": 50.97, "sma20": 50.67, "sma30": 49.66, "sma50": 48.12, "sma100": 46.63, "sma200": 44.21, "sector": "Utilities", "indices": []}, {"ticker": "NBIS", "name": "Nebius Group N.V.", "price": 115.76, "change": -14.09, "changePercent": -10.85, "change5dPercent": 20.05, "marketCap": 29356294446, "volume": 24056104, "avgVolume10d": 16888940, "avgVolume60d": 13295086, "avgVolume90d": 15740735, "avgTradingValue": 1557216382, "sma10": 105.27, "sma20": 102.16, "sma30": 97.8, "sma50": 97.87, "sma100": 97.81, "sma200": 85.29, "sector": "Communication Services", "indices": []}, {"ticker": "PPL", "name": "PPL Corporation", "price": 38.82, "change": 0.08, "changePercent": 0.21, "change5dPercent": 2.59, "marketCap": 29180755915, "volume": 987905, "avgVolume10d": 7544020, "avgVolume60d": 8668960, "avgVolume90d": 8169766, "avgTradingValue": 409685991, "sma10": 38.19, "sma20": 37.93, "sma30": 37.26, "sma50": 36.58, "sma100": 35.9, "sma200": 35.43, "sector": "Utilities", "indices": []}, {"ticker": "DVN", "name": "Devon Energy Corporation", "price": 47.01, "change": 0.36, "changePercent": 0.77, "change5dPercent": 8.14, "marketCap": 29133815914, "volume": 3305405, "avgVolume10d": 15735840, "avgVolume60d": 11356338, "avgVolume90d": 10453594, "avgTradingValue": 612514366, "sma10": 45.08, "sma20": 44.34, "sma30": 44.02, "sma50": 41.35, "sma100": 38.2, "sma200": 35.66, "sector": "Energy", "indices": []}, {"ticker": "CNP", "name": "CenterPoint Energy, Inc (Holdin", "price": 44.1, "change": -0.03, "changePercent": -0.08, "change5dPercent": 2.19, "marketCap": 28868224700, "volume": 569932, "avgVolume10d": 4033673, "avgVolume60d": 5359700, "avgVolume90d": 5094309, "avgTradingValue": 248212258, "sma10": 43.63, "sma20": 43.29, "sma30": 42.45, "sma50": 40.96, "sma100": 39.76, "sma200": 38.48, "sector": "Utilities", "indices": []}, {"ticker": "TS", "name": "Tenaris S.A.", "price": 55.7, "change": 1.86, "changePercent": 3.45, "change5dPercent": 3.61, "marketCap": 28098274332, "volume": 657634, "avgVolume10d": 1874253, "avgVolume60d": 1529087, "avgVolume90d": 1339629, "avgTradingValue": 101526479, "sma10": 53.61, "sma20": 53.5, "sma30": 51.47, "sma50": 47.91, "sma100": 43.73, "sma200": 39.88, "sector": "Energy", "indices": []}, {"ticker": "DOW", "name": "Dow Inc.", "price": 37.47, "change": 1.47, "changePercent": 4.07, "change5dPercent": 10.55, "marketCap": 26993066965, "volume": 2645257, "avgVolume10d": 17292175, "avgVolume60d": 13150865, "avgVolume90d": 13006042, "avgTradingValue": 480069211, "sma10": 34.96, "sma20": 32.69, "sma30": 32.39, "sma50": 30.17, "sma100": 26.47, "sma200": 25.42, "sector": "Basic Materials", "indices": []}, {"ticker": "CTRA", "name": "Coterra Energy Inc.", "price": 32.69, "change": 0.33, "changePercent": 1.0, "change5dPercent": 8.3, "marketCap": 24828218359, "volume": 1955772, "avgVolume10d": 11757847, "avgVolume60d": 10607867, "avgVolume90d": 9491231, "avgTradingValue": 309693265, "sma10": 31.37, "sma20": 31.01, "sma30": 30.81, "sma50": 28.98, "sma100": 27.24, "sma200": 25.57, "sector": "Energy", "indices": []}, {"ticker": "MRNA", "name": "Moderna, Inc.", "price": 54.92, "change": 1.61, "changePercent": 3.02, "change5dPercent": -0.11, "marketCap": 21709504238, "volume": 1263605, "avgVolume10d": 9860270, "avgVolume60d": 11680561, "avgVolume90d": 11185091, "avgTradingValue": 508379825, "sma10": 54.5, "sma20": 52.57, "sma30": 48.96, "sma50": 46.03, "sma100": 36.61, "sma200": 32.1, "sector": "Healthcare", "indices": []}, {"ticker": "ROIV", "name": "Roivant Sciences Ltd.", "price": 28.41, "change": 0.13, "changePercent": 0.46, "change5dPercent": -4.34, "marketCap": 20311597667, "volume": 931328, "avgVolume10d": 6128212, "avgVolume60d": 6433130, "avgVolume90d": 7017295, "avgTradingValue": 158646830, "sma10": 29.01, "sma20": 28.52, "sma30": 27.43, "sma50": 25.44, "sma100": 23.08, "sma200": 17.93, "sector": "Healthcare", "indices": []}, {"ticker": "EXAS", "name": "Exact Sciences Corporation", "price": 103.87, "change": 0.02, "changePercent": 0.02, "change5dPercent": 0.48, "marketCap": 19828512917, "volume": 526136, "avgVolume10d": 2121793, "avgVolume60d": 2323325, "avgVolume90d": 4323007, "avgTradingValue": 224999336, "sma10": 103.54, "sma20": 103.44, "sma30": 103.31, "sma50": 102.87, "sma100": 94.94, "sma200": 73.57, "sector": "Healthcare", "indices": []}, {"ticker": "AA", "name": "Alcoa Corporation", "price": 67.66, "change": 1.06, "changePercent": 1.59, "change5dPercent": 10.36, "marketCap": 17933187585, "volume": 1470996, "avgVolume10d": 6684199, "avgVolume60d": 7505613, "avgVolume90d": 7009789, "avgTradingValue": 405534124, "sma10": 63.38, "sma20": 62.64, "sma30": 61.73, "sma50": 61.74, "sma100": 52.19, "sma200": 41.62, "sector": "Basic Materials", "indices": []}, {"ticker": "PR", "name": "Permian Resources Corporation", "price": 19.56, "change": 0.33, "changePercent": 1.69, "change5dPercent": 4.46, "marketCap": 16589319993, "volume": 1945469, "avgVolume10d": 13471206, "avgVolume60d": 11784224, "avgVolume90d": 11403428, "avgTradingValue": 246741090, "sma10": 19.07, "sma20": 18.54, "sma30": 17.98, "sma50": 16.64, "sma100": 15.13, "sma200": 14.21, "sector": "Energy", "indices": []}, {"ticker": "KIM", "name": "Kimco Realty Corporation (HC)", "price": 23.41, "change": 0.22, "changePercent": 0.93, "change5dPercent": 1.06, "marketCap": 15853112677, "volume": 587584, "avgVolume10d": 5023678, "avgVolume60d": 5666201, "avgVolume90d": 5327620, "avgTradingValue": 148729322, "sma10": 23.18, "sma20": 23.1, "sma30": 22.65, "sma50": 21.78, "sma100": 20.96, "sma200": 20.92, "sector": "Real Estate", "indices": []}, {"ticker": "OVV", "name": "Ovintiv Inc. (DE)", "price": 55.9, "change": 1.06, "changePercent": 1.93, "change5dPercent": 6.25, "marketCap": 15831369051, "volume": 730860, "avgVolume10d": 4750266, "avgVolume60d": 4629709, "avgVolume90d": 4330676, "avgTradingValue": 275388485, "sma10": 53.72, "sma20": 51.95, "sma30": 49.95, "sma50": 46.04, "sma100": 42.29, "sma200": 40.79, "sector": "Energy", "indices": []}, {"ticker": "PAA", "name": "Plains All American Pipeline, L", "price": 21.62, "change": 0.38, "changePercent": 1.79, "change5dPercent": 2.56, "marketCap": 15275254537, "volume": 532159, "avgVolume10d": 4296995, "avgVolume60d": 3530709, "avgVolume90d": 3265467, "avgTradingValue": 74482564, "sma10": 21.56, "sma20": 21.19, "sma30": 20.72, "sma50": 19.88, "sma100": 18.34, "sma200": 17.53, "sector": "Energy", "indices": []}, {"ticker": "AKAM", "name": "Akamai Technologies, Inc.", "price": 104.27, "change": -1.17, "changePercent": -1.11, "change5dPercent": -0.22, "marketCap": 15130665789, "volume": 1246306, "avgVolume10d": 3292200, "avgVolume60d": 3807740, "avgVolume90d": 3846637, "avgTradingValue": 473316835, "sma10": 103.98, "sma20": 102.49, "sma30": 100.96, "sma50": 97.88, "sma100": 91.14, "sma200": 84.1, "sector": "Technology", "indices": []}, {"ticker": "APA", "name": "APA Corporation", "price": 35.79, "change": 1.25, "changePercent": 3.62, "change5dPercent": 12.48, "marketCap": 12648169205, "volume": 1596189, "avgVolume10d": 7943088, "avgVolume60d": 6741483, "avgVolume90d": 6796823, "avgTradingValue": 264211717, "sma10": 33.2, "sma20": 31.34, "sma30": 30.0, "sma50": 28.15, "sma100": 26.16, "sma200": 23.33, "sector": "Energy", "indices": []}, {"ticker": "CFLT", "name": "Confluent, Inc.", "price": 30.99, "change": 0.32, "changePercent": 1.04, "change5dPercent": 0.78, "marketCap": 11133730691, "volume": 18291400, "avgVolume10d": 8949550, "avgVolume60d": 12302750, "avgVolume90d": 12934107, "avgTradingValue": 265695032, "sma10": 30.76, "sma20": 30.72, "sma30": 30.64, "sma50": 30.56, "sma100": 27.91, "sma200": 24.82, "sector": "Technology", "indices": []}, {"ticker": "DINO", "name": "HF Sinclair Corporation", "price": 58.57, "change": 1.98, "changePercent": 3.5, "change5dPercent": 10.26, "marketCap": 10765570617, "volume": 520308, "avgVolume10d": 3112530, "avgVolume60d": 2929965, "avgVolume90d": 2831218, "avgTradingValue": 212271421, "sma10": 56.05, "sma20": 53.36, "sma30": 54.55, "sma50": 52.48, "sma100": 51.56, "sma200": 48.38, "sector": "Energy", "indices": []}, {"ticker": "BRX", "name": "Brixmor Property Group Inc.", "price": 30.09, "change": 0.12, "changePercent": 0.42, "change5dPercent": 0.69, "marketCap": 9226818556, "volume": 773386, "avgVolume10d": 2449468, "avgVolume60d": 2949178, "avgVolume90d": 2875554, "avgTradingValue": 88312809, "sma10": 30.0, "sma20": 30.0, "sma30": 29.47, "sma50": 28.16, "sma100": 27.03, "sma200": 26.49, "sector": "Real Estate", "indices": []}, {"ticker": "DAR", "name": "Darling Ingredients Inc.", "price": 57.6, "change": 2.39, "changePercent": 4.33, "change5dPercent": 9.51, "marketCap": 9129220440, "volume": 792292, "avgVolume10d": 3252749, "avgVolume60d": 2519124, "avgVolume90d": 2398841, "avgTradingValue": 145763861, "sma10": 54.34, "sma20": 53.48, "sma30": 51.99, "sma50": 47.69, "sma100": 41.2, "sma200": 37.29, "sector": "Consumer Defensive", "indices": []}, {"ticker": "PL", "name": "Planet Labs PBC", "price": 26.28, "change": 1.68, "changePercent": 6.83, "change5dPercent": 3.46, "marketCap": 8970667370, "volume": 4252840, "avgVolume10d": 9125094, "avgVolume60d": 11492372, "avgVolume90d": 11324764, "avgTradingValue": 230531482, "sma10": 25.32, "sma20": 25.02, "sma30": 24.11, "sma50": 24.64, "sma100": 19.51, "sma200": 13.87, "sector": "Industrials", "indices": []}, {"ticker": "JHG", "name": "Janus Henderson Group plc", "price": 51.74, "change": 1.28, "changePercent": 2.55, "change5dPercent": 1.72, "marketCap": 7972488180, "volume": 3140510, "avgVolume10d": 2395631, "avgVolume60d": 2435421, "avgVolume90d": 1924016, "avgTradingValue": 164510004, "sma10": 50.96, "sma20": 50.82, "sma30": 50.03, "sma50": 49.2, "sma100": 46.78, "sma200": 44.09, "sector": "Financial Services", "indices": []}, {"ticker": "NE", "name": "Noble Corporation plc A", "price": 47.65, "change": 1.44, "changePercent": 3.12, "change5dPercent": 4.59, "marketCap": 7585756257, "volume": 580637, "avgVolume10d": 1524653, "avgVolume60d": 2052630, "avgVolume90d": 1911338, "avgTradingValue": 85130292, "sma10": 45.7, "sma20": 45.31, "sma30": 43.76, "sma50": 39.21, "sma100": 34.23, "sma200": 30.69, "sector": "Energy", "indices": []}, {"ticker": "VIAV", "name": "Viavi Solutions Inc.", "price": 31.74, "change": 0.14, "changePercent": 0.44, "change5dPercent": 6.8, "marketCap": 7341983810, "volume": 1306703, "avgVolume10d": 4282910, "avgVolume60d": 4752421, "avgVolume90d": 4485258, "avgTradingValue": 173490773, "sma10": 30.36, "sma20": 29.96, "sma30": 28.74, "sma50": 25.12, "sma100": 21.15, "sma200": 16.05, "sector": "Technology", "indices": []}, {"ticker": "VIST", "name": "Vista Energy S.A.B. de C.V.", "price": 68.25, "change": 2.56, "changePercent": 3.89, "change5dPercent": 15.79, "marketCap": 7245190284, "volume": 749250, "avgVolume10d": 1955825, "avgVolume60d": 1307855, "avgVolume90d": 1176966, "avgTradingValue": 106383393, "sma10": 62.3, "sma20": 60.0, "sma30": 58.41, "sma50": 55.69, "sma100": 51.94, "sma200": 47.15, "sector": "Energy", "indices": []}, {"ticker": "AAOI", "name": "Applied Optoelectronics, Inc.", "price": 89.71, "change": -4.36, "changePercent": -4.64, "change5dPercent": -25.55, "marketCap": 7042027116, "volume": 5705880, "avgVolume10d": 12052068, "avgVolume60d": 7133853, "avgVolume90d": 6573154, "avgTradingValue": 1042103306, "sma10": 104.13, "sma20": 84.38, "sma30": 71.11, "sma50": 57.69, "sma100": 43.73, "sma200": 34.4, "sector": "Technology", "indices": []}, {"ticker": "CENX", "name": "Century Aluminum Company", "price": 58.89, "change": 3.24, "changePercent": 5.82, "change5dPercent": 9.95, "marketCap": 5816209811, "volume": 522006, "avgVolume10d": 2343670, "avgVolume60d": 2313291, "avgVolume90d": 2330664, "avgTradingValue": 133637869, "sma10": 55.41, "sma20": 53.79, "sma30": 52.59, "sma50": 50.18, "sma100": 40.83, "sma200": 31.93, "sector": "Basic Materials", "indices": []}, {"ticker": "MGY", "name": "Magnolia Oil & Gas Corporation", "price": 30.05, "change": 0.66, "changePercent": 2.25, "change5dPercent": 4.52, "marketCap": 5664997398, "volume": 654110, "avgVolume10d": 3210551, "avgVolume60d": 2972178, "avgVolume90d": 2737845, "avgTradingValue": 89595750, "sma10": 29.18, "sma20": 28.3, "sma30": 27.67, "sma50": 25.87, "sma100": 24.12, "sma200": 23.68, "sector": "Energy", "indices": []}, {"ticker": "PBF", "name": "PBF Energy Inc.", "price": 44.32, "change": 0.75, "changePercent": 1.72, "change5dPercent": 11.78, "marketCap": 5169334339, "volume": 662352, "avgVolume10d": 4547115, "avgVolume60d": 3436310, "avgVolume90d": 3196615, "avgTradingValue": 150446638, "sma10": 42.78, "sma20": 39.16, "sma30": 37.59, "sma50": 35.18, "sma100": 33.8, "sma200": 29.39, "sector": "Energy", "indices": []}, {"ticker": "LBRT", "name": "Liberty Energy Inc.", "price": 31.53, "change": 1.51, "changePercent": 5.03, "change5dPercent": 11.33, "marketCap": 5094900063, "volume": 1306094, "avgVolume10d": 3894679, "avgVolume60d": 4196966, "avgVolume90d": 4014642, "avgTradingValue": 103703013, "sma10": 29.02, "sma20": 28.29, "sma30": 27.17, "sma50": 24.69, "sma100": 21.2, "sma200": 16.51, "sector": "Energy", "indices": []}, {"ticker": "TERN", "name": "Terns Pharmaceuticals, Inc.", "price": 46.58, "change": 0.51, "changePercent": 1.1, "change5dPercent": 2.84, "marketCap": 5084870386, "volume": 787470, "avgVolume10d": 2047847, "avgVolume60d": 2157162, "avgVolume90d": 2971701, "avgTradingValue": 85522825, "sma10": 44.71, "sma20": 42.77, "sma30": 41.1, "sma50": 39.12, "sma100": 33.51, "sma200": 19.82, "sector": "Healthcare", "indices": []}, {"ticker": "ALM", "name": "Almonty Industries Inc.", "price": 18.71, "change": -0.58, "changePercent": -3.01, "change5dPercent": -12.12, "marketCap": 4697593845, "volume": 3434662, "avgVolume10d": 5626166, "avgVolume60d": 4603017, "avgVolume90d": 3870328, "avgTradingValue": 98795770, "sma10": 19.96, "sma20": 18.42, "sma30": 16.84, "sma50": 14.14, "sma100": 10.68, "sma200": 8.03, "sector": "Basic Materials", "indices": []}, {"ticker": "FOLD", "name": "Amicus Therapeutics, Inc.", "price": 14.39, "change": 0.02, "changePercent": 0.1, "change5dPercent": 0.17, "marketCap": 4516900313, "volume": 837631, "avgVolume10d": 3674393, "avgVolume60d": 10532773, "avgVolume90d": 8810528, "avgTradingValue": 51613169, "sma10": 14.36, "sma20": 14.35, "sma30": 14.34, "sma50": 14.32, "sma100": 12.36, "sma200": 9.7, "sector": "Healthcare", "indices": []}, {"ticker": "CRGY", "name": "Crescent Energy Company", "price": 12.23, "change": 0.43, "changePercent": 3.64, "change5dPercent": 4.44, "marketCap": 4011859715, "volume": 1810529, "avgVolume10d": 11997972, "avgVolume60d": 7250170, "avgVolume90d": 6754536, "avgTradingValue": 115702820, "sma10": 11.79, "sma20": 11.26, "sma30": 10.83, "sma50": 9.9, "sma100": 9.3, "sma200": 9.02, "sector": "Energy", "indices": []}, {"ticker": "PTEN", "name": "Patterson-UTI Energy, Inc.", "price": 10.52, "change": 0.38, "changePercent": 3.7, "change5dPercent": 10.68, "marketCap": 3976050364, "volume": 2530646, "avgVolume10d": 11493684, "avgVolume60d": 10703747, "avgVolume90d": 9823037, "avgTradingValue": 95770833, "sma10": 9.61, "sma20": 9.0, "sma30": 8.71, "sma50": 8.05, "sma100": 7.0, "sma200": 6.3, "sector": "Energy", "indices": []}, {"ticker": "LASR", "name": "nLIGHT, Inc.", "price": 67.67, "change": -0.83, "changePercent": -1.21, "change5dPercent": 6.08, "marketCap": 3773166750, "volume": 628868, "avgVolume10d": 2028336, "avgVolume60d": 1434176, "avgVolume90d": 1222504, "avgTradingValue": 139734993, "sma10": 64.1, "sma20": 61.5, "sma30": 57.96, "sma50": 52.12, "sma100": 43.21, "sma200": 33.72, "sector": "Technology", "indices": []}, {"ticker": "FSLY", "name": "Fastly, Inc.", "price": 23.46, "change": 0.67, "changePercent": 2.94, "change5dPercent": 3.17, "marketCap": 3556674046, "volume": 3868985, "avgVolume10d": 11018748, "avgVolume60d": 9895688, "avgVolume90d": 8537549, "avgTradingValue": 270466921, "sma10": 22.43, "sma20": 20.57, "sma30": 17.47, "sma50": 14.29, "sma100": 12.3, "sma200": 9.92, "sector": "Technology", "indices": []}], "totalUniverse": 5780, "totalPassing": 71, "lastUpdated": "2026-03-17T15:02:24.288227"}